{"forecast_time": "2025-09-23 12:00 UTC", "storm_names": ["GABRIELLE", "NARDA", "RAGASA", "NEOGURI"], "storm_data": {"GABRIELLE": {"countries_affected": ["Portugal"], "countries_displaced": ["Portugal"]}, "NARDA": {"countries_affected": [], "countries_displaced": []}, "RAGASA": {"countries_affected": ["China", "Hong Kong", "Lao People's Democratic Republic", "Viet Nam"], "countries_displaced": ["China", "Hong Kong", "Lao People's Democratic Republic", "Viet Nam"]}, "NEOGURI": {"countries_affected": [], "countries_displaced": []}}, "storms_affecting_people": ["GABRIELLE", "RAGASA"], "storms_displacing_people": ["GABRIELLE", "RAGASA"], "number_active": 4, "number_affecting_people": 2, "number_displacing_people": 2}