{"forecast_time": "2025-10-10 00:00 UTC", "storm_names": ["RAYMOND", "OCTAVE", "HALONG", "JERRY", "PRISCILLA", "NAKRI"], "storm_data": {"RAYMOND": {"countries_affected": [], "countries_displaced": []}, "OCTAVE": {"countries_affected": [], "countries_displaced": []}, "HALONG": {"countries_affected": [], "countries_displaced": []}, "JERRY": {"countries_affected": ["Antigua and Barbuda"], "countries_displaced": ["Antigua and Barbuda"]}, "PRISCILLA": {"countries_affected": [], "countries_displaced": []}, "NAKRI": {"countries_affected": ["Japan"], "countries_displaced": ["Japan"]}}, "storms_affecting_people": ["JERRY", "NAKRI"], "storms_displacing_people": ["JERRY", "NAKRI"], "number_active": 6, "number_affecting_people": 2, "number_displacing_people": 2}